{
  "name": "Ella Brady",
  "age": 34,
  "address": {
    "street": "Fijo Junction",
    "city": "Tovduep",
    "state": "AZ",
    "zip": "37956"
  },
  "contact": {
    "phone": "(380) 684-4565",
    "servicePhone": "800937199"
  },
  "birthday": "1960-05-17T04:51:24.707Z",
  "ip": "196.235.100.74",
  "foo": "bar",
  "profile": {
    "about": "Mefap copwirna ivbut hul gejve cubcug nekfocat tukbuthol kew wadehe jo vuuvow ufaisiid leawa efcunpes awutebjuk uh ke. Otigupeh lo folpenno riddufip uc vejtudzoc ci oflafob ge ha ip utpiw ricosol ja fooza. Paf nedmiweh bomjig nouhdu utpisda colravdid sobe has azufare aji waci juweg soh nefgosu sobidzap. Abiudosac wuzkoti fehca ipukon gadtonim voc li fas hitu ritimbec daf am duw ti ivafod. Sesbej samwuz haidlu sonece nasijoli huho fofawtig zaha bi ik korazo ma mu zebhuj sozichaz elju kumwi cecevur. Hi buwdedav siggis dipsuli pokcer aso naw temu iwmobuke poc ukeci mivole zambeh zija un his kab. Apficwe ropgo mec orgub movwe re ebteap rerupwar vel supu sauwikim ruk cocvur.",
    "bio": "Wowikfur ju gor luraf li hukeb elu fu kakef rah foh to jajahif. Gije lipcogop bo gib memudoono wuh ozu vedgalja ena ol daz tuge ubalewa wanva ga. Duebesi ge ri leagmuk gewooka wa zonfivwuw izhitna zugeso affa caawa gu. Gupzup da ezi ledur karueho vuri zodpise osuva oziku atuwip ve cuvriso."
  },
  "apiKey": "db3ebebfa94984b30b8c0b313ac5fb8990dc2cd8b0fe4777d0d4b397401685d9",
  "currency": {
    "code": "SRD",
    "name": "Suriname Dollar"
  }
}